{"name":"ilDeposito.org","tagline":"Canti di protesta politica e sociale","body":"### Cosa è ilDeposito.org\r\nilDeposito.org è un archivio di canti di protesta politica e sociale (http://www.ildeposito.org).\r\nIl sito è basato sulla piattaforma [Drupal](http://www.drupal.org) e lo sviluppatore (@sedurzu) ha deciso di rendere disponibile il codice sorgente del sito.\r\n\r\n### Come utilizzare questo repository\r\nQuesto repository mette a disposizione la document root dell'applicazione, in particolare:\r\n* il **core** di Drupal\r\n* tutti i **moduli** (sia \"contrib\" che custom)\r\n* tutti i **temi** (sia \"contrib\" che custom)\r\n* tutte le **librerie**\r\n* tutte le [Features](http://www.drupal.org/project/features) delle configurazioni dell'applicazione\r\n\r\nCon questi elementi è possibile replicare l'applicazione (ovviamente senza contenuti).\r\nPer fare questo è necessario avere un webserver **Apache**, **Mysql**, **PHP** e il motore di ricerca **ApacheSOLR**.\r\n\r\nPer tutti i riferimenti tecnici si rimanda al sito ufficiale di Drupal: http://www.drupal.org\r\n\r\nPer maggior informazioni si invita a contattare lo sviluppatore direttamente dal sito http://www.ildeposito.org\r\n\r\n### Chi è lo sviluppatore\r\nSergio Durzu progetta e sviluppa applicazioni web, soprattutto con Drupal, presso una società IT sarda ed è un sostenitore del software libero.","google":"UA-20117666-1","note":"Don't delete this file! It's used internally to help with page regeneration."}